README.md
setup.py
lingkar33423324/__init__.py
lingkar33423324/hitung_luas_lingkaran.py
lingkar33423324.egg-info/PKG-INFO
lingkar33423324.egg-info/SOURCES.txt
lingkar33423324.egg-info/dependency_links.txt
lingkar33423324.egg-info/requires.txt
lingkar33423324.egg-info/top_level.txt