Metadata-Version: 2.1
Name: lingkar33423324
Version: 0.0.1
Requires-Dist: math
